{"sections":{"main":{"type":"main-product","blocks":{"badge_Hkd38r":{"type":"badge","settings":{"spacing_bottom":"1","show_badges":true,"show_badges_discount":true,"show_badges_sold":true}},"1e0c79e9-7de0-4eee-b9c5-f27132635fb8":{"type":"title","settings":{"heading_size":"h6","spacing_bottom":"1"}},"1e939cd6-0958-4135-a9e5-c50faef01437":{"type":"variant_picker","settings":{"spacing_bottom":"4","title":"Variant picker","enable_back_in_stock":false,"picker_type":"swatch","variant_options_with_thumbnails":"Color","size_guide_page":"size-guide","sizes_option":"Size"}},"8effeb43-55b7-4ec4-ab9b-68bcd89b865b":{"type":"price","settings":{"spacing_bottom":"1","show_price_tax_info":true,"show_price_shipping_info":false,"show_price_custom_info":""}},"globo_product_options_app_block_xcaVQg":{"type":"shopify:\/\/apps\/globo-product-options\/blocks\/app-block\/fdc9fad5-1a0f-4bd4-9c8a-1af6a6eef6b8","settings":{}},"description_qA3HqH":{"type":"description","settings":{"spacing_bottom":"1","behaviour":"plain","heading":"","text_truncate":0,"icon":"theme-box","metafield_for_product_variant":"","show_block_content":true}},"8604a6ff-ad0b-44dd-8068-1de4e062f8e8":{"type":"buy_buttons","settings":{"spacing_bottom":"2","show_quantity":true,"layout":"seperate","show_dynamic_checkout":true,"show_gift_card_recipient":false}},"1e939cd6-0955-4135-a9e5-c50faef01437":{"type":"purchase_options","settings":{"spacing_bottom":"1","show_subscription_title":true,"show_subscription_custom_info":"","show_subscription_policy":true}},"e6d841d6-2f71-40b3-956a-912df13f9f6e":{"type":"inventory_notice","settings":{"spacing_bottom":"1","inventory_threshold":15,"notice_just_text":false}},"content_grid_W3Mqy6":{"type":"content_grid","disabled":true,"settings":{"heading":"fast global shipping","icon":"theme-box"}},"content_grid_iCJFCN":{"type":"content_grid","settings":{"heading":"local business","icon":"theme-box"}},"content_grid_HTRRPP":{"type":"content_grid","disabled":true,"settings":{"heading":"100% secure payments","icon":"theme-box"}},"content_grid_AAkHkC":{"type":"content_grid","disabled":true,"settings":{"heading":"Free climate compensated shipping","icon":"theme-box"}},"complementary_products_tKerNK":{"type":"complementary_products","disabled":true,"settings":{"spacing_bottom":"1","heading":"You may also like","icon":"theme-box","limit":4}}},"block_order":["badge_Hkd38r","1e0c79e9-7de0-4eee-b9c5-f27132635fb8","1e939cd6-0958-4135-a9e5-c50faef01437","8effeb43-55b7-4ec4-ab9b-68bcd89b865b","globo_product_options_app_block_xcaVQg","description_qA3HqH","8604a6ff-ad0b-44dd-8068-1de4e062f8e8","1e939cd6-0955-4135-a9e5-c50faef01437","e6d841d6-2f71-40b3-956a-912df13f9f6e","content_grid_W3Mqy6","content_grid_iCJFCN","content_grid_HTRRPP","content_grid_AAkHkC","complementary_products_tKerNK"],"settings":{"product_media_layout":"product__media-layout--full","product_media_layout_mobile":"product__media-layout--full--sm","product_media_aspect_ratio":"fit","product_media_object_fit":"cover","product_slider_auto_height":false,"media_transparent_background":true,"display_media_zoom":"click","product_media_with_thumbs":"only_mobile","product_media_thumbs_ratio":"square","product_media_thumbs_object_fit":"contain","gallery_arrows_show_on":"desktop","display_media_gallery_pagination":"none","media_gallery_info":"","metafield_as_seen_on":"theme.as_seen_on","color_scheme_gallery":"","enable_sticky_info":true,"enable_actions_bar":true,"media_grid_size":"large","media_grid_position":"start","grid_gap":"2","spacing_grid":1.6,"grid_content_alignment":"start","section_width":"max-w-fluid","color_scheme":"scheme-1","spacing_top":"2","spacing_bottom":"0"}},"complete_the_set_QRxhyG":{"type":"complete-the-set","blocks":{"collapsible_Y3m9DD":{"type":"collapsible","settings":{"block_type":"collapsible","heading":"Warranty, Returns and Exchanges","link":"","content":"<p>You can view our whole warranty policy <a href=\"\/pages\/warranty-new-delete-old-when-swap\" target=\"_blank\" title=\"Warranty\">here.<\/a> Cameras come with a variable based warranty and are guaranteed working and fully refurbished. <br\/><br\/>We accept returns by choice on cameras and non film items 14 days after sale with a 15% restocking fee. Returned items must be brought back to us in the same physical condition they got to you.<\/p>","page":""}},"collapsible_RLd3Xc":{"type":"collapsible","settings":{"block_type":"collapsible","heading":"Delivery & Pickup","link":"","content":"<p>We ship most orders same day, but our processing times are based on 2 day delivery. We delivery via USPS & UPS or whatever carrier you select. Most domestic shipments are delivered within 2-4 days.<br\/><br\/>It is always free to choose pickup in store and your item is typically ready within a few hours<\/p>","page":""}}},"block_order":["collapsible_Y3m9DD","collapsible_RLd3Xc"],"disabled":true,"settings":{"heading":"More info","content_heading":"Similar items","heading_size":"h5","content_type":"products","featured_image_aspect_ratio":"4\/3","open_first_collapsible":false,"flip_desktop":true,"flip_mobile":true,"section_width":"max-w-fluid","color_scheme":"","spacing_top":"6","spacing_bottom":"2"}},"multitile_KDV8BX":{"type":"multitile","blocks":{"tile_qpzFf7":{"type":"tile","settings":{"show_on":"both","column_factor":3,"row_factor":1,"color_scheme":"","gradient_background_color":"","tile_aspect_ratio":"1\/1","content_position_vertical":"justify-center","content_alignment":"align-center text-center","content_alignment_for_mobile":"start","media_position":"background","heading":"","heading_size":"h3","text":"","button_label":"","button_link":"","button_style":"button--filled","video_external":"","show_controls_on_video":false,"video_external_mobile":"","show_controls_on_video_mobile":false,"spacing_inner":"2"}},"tile_kkJDV4":{"type":"tile","settings":{"show_on":"both","column_factor":3,"row_factor":2,"color_scheme":"","gradient_background_color":"","tile_aspect_ratio":"auto","content_position_vertical":"justify-center","content_alignment":"align-center text-center","content_alignment_for_mobile":"start","media_position":"background","heading":"","heading_size":"h3","text":"","button_label":"","button_link":"","button_style":"button--filled","video_external":"","show_controls_on_video":false,"video_external_mobile":"","show_controls_on_video_mobile":false,"spacing_inner":"2"}},"tile_aT3xD9":{"type":"tile","settings":{"show_on":"both","column_factor":3,"row_factor":1,"color_scheme":"scheme-8","gradient_background_color":"","tile_aspect_ratio":"auto","content_position_vertical":"justify-center","content_alignment":"align-center text-center","content_alignment_for_mobile":"start","media_position":"background","heading":"Amazing details. Organic fabrics.","heading_size":"h3","text":"","button_label":"","button_link":"","button_style":"button--filled","video_external":"","show_controls_on_video":false,"video_external_mobile":"","show_controls_on_video_mobile":false,"spacing_inner":"6"}}},"block_order":["tile_qpzFf7","tile_kkJDV4","tile_aT3xD9"],"disabled":true,"settings":{"block_order_mobile":false,"heading":"","heading_size":"h3","heading_alignment":"start","spacing_tile":"default","color_scheme":"","section_width":"max-w-fluid","spacing_top":"2","spacing_bottom":"2"}},"166904322806a89075":{"type":"apps","settings":{"section_layout":"normal","spacing_inner":"2","section_width":"max-w-page","color_scheme":"","spacing_top":"2","spacing_bottom":"2"}},"complete_the_set_Mf7jik":{"type":"complete-the-set","blocks":{"collapsible_QQzpVG":{"type":"collapsible","settings":{"block_type":"collapsible","heading":"Description","link":"","content":"<p>[description]<\/p>","page":""}},"collapsible_4ijA4L":{"type":"collapsible","settings":{"block_type":"drawer","heading":"Delivery & Returns","link":"","content":"<p>Shipping and returns can be inserted here.<\/p>","page":""}},"collapsible_xFw8rk":{"type":"collapsible","settings":{"block_type":"drawer","heading":"Contact us","link":"","content":"<p>Contact information can be entered here.<\/p>","page":""}}},"block_order":["collapsible_QQzpVG","collapsible_4ijA4L","collapsible_xFw8rk"],"disabled":true,"name":"t:sections.complete-the-set.name","settings":{"heading":"More info","content_heading":"Similar items","heading_size":"h3","content_type":"products","featured_image_aspect_ratio":"4\/3","open_first_collapsible":true,"flip_desktop":true,"flip_mobile":true,"section_width":"max-w-page","color_scheme":"","spacing_top":"2","spacing_bottom":"2"}},"custom_liquid_RbMQXt":{"type":"custom-liquid","name":"t:sections.custom-liquid.name","settings":{"custom_liquid":"<style>\n  .bfc-warning-box {\n    border: 2px solid #c2410c;\n    background-color: #fff7ed;\n    padding: 1.25rem 1.5rem;\n    border-radius: 6px;\n    font-size: 0.95rem;\n    line-height: 1.5;\n    margin: 1.5rem 0;\n  }\n\n  .bfc-warning-box__title {\n    font-weight: 700;\n    text-transform: uppercase;\n    letter-spacing: 0.05em;\n    margin-bottom: 0.75rem;\n  }\n\n  .bfc-warning-box__list {\n    margin: 0 0 0.75rem 1.25rem;\n    padding: 0;\n  }\n\n  .bfc-warning-box__list li {\n    margin-bottom: 0.5rem;\n  }\n\n  .bfc-warning-box__address {\n    font-weight: 600;\n    margin-top: 0.25rem;\n    margin-bottom: 0.25rem;\n  }\n\n  .bfc-warning-box__note {\n    font-size: 0.9rem;\n    margin-top: 0.5rem;\n  }\n<\/style>\n\n<div class=\"bfc-warning-box\" id=\"mailing-film-warning\">\n  <div class=\"bfc-warning-box__title\">\n    Mailing us your film? Please read:\n  <\/div>\n\n  <ul class=\"bfc-warning-box__list\">\n    <li>\n      Only ship to:\n      <div class=\"bfc-warning-box__address\">\n        Developing @ BFC<br>\n        697 Grand St #119<br>\n        Brooklyn, NY 11211\n      <\/div>\n      Any other address will not reach us.\n    <\/li>\n    <li>\n      Include your order number inside your package.\n    <\/li>\n    <li>\n      Fill out all options and pay for return shipping if you want your negatives returned.\n    <\/li>\n  <\/ul>\n\n  <p class=\"bfc-warning-box__note\">\n    Want the negatives discarded instead? Choose <strong>Pick up in store<\/strong> on the shipping page.\n  <\/p>\n<\/div>","section_width":"max-w-page","color_scheme":"","spacing_top":"2","spacing_bottom":"2"}},"175641204134f8dd6a":{"type":"apps","blocks":{"subi_subscriptions_app_block_nptcyw":{"type":"shopify:\/\/apps\/subi-subscriptions\/blocks\/app-block\/bc0dba25-cd46-4841-bea4-6bdfe9ac815f","settings":{"product":"{{product}}","use_app_block_wording":false,"widget_label":"Purchase options","one_time_purchase_text":"One-Time Purchase","subscription_text":"Subscribe and save","delivery_frequency_text":"Delivery frequency","prepaid_subscription_text":"Subscription with prepaid","skin1_priceSuffix":"each","skin1_save":"Save(skin1)","skin1_prepaid_payment_title":"prepaid","skin1_normal_payment_title":"pay as you go","skin2_discountSuffix":"Save","skin3_fullPrice":"Full price","skin3_priceSuffix":"each","skin3_discountSuffix":"Off","skin4_justOnce":"Just once","skin4_discountSuffix":"Off","skin4_priceSuffix":"each","skin4_fullPrice":"(Full price)","skin4_sellingPlansTitle":"Renews every:","from":"from","max_discount_badge_title":"UP To","pay":"Pay","price_save_up_to":"save up to"}}},"block_order":["subi_subscriptions_app_block_nptcyw"],"disabled":true,"settings":{"section_layout":"normal","spacing_inner":"2","section_width":"max-w-page","color_scheme":"","spacing_top":"2","spacing_bottom":"2"}}},"order":["main","complete_the_set_QRxhyG","multitile_KDV8BX","166904322806a89075","complete_the_set_Mf7jik","custom_liquid_RbMQXt","175641204134f8dd6a"]}